src/__init__.py
src/connector.py
src/http_delivery.py
src/launcher.py
src/package_info.py
src/server_config.py
src/version_checker.py
ur_tunnel-0.0.13.dist-info/METADATA
ur_tunnel-0.0.13.dist-info/WHEEL
ur_tunnel-0.0.13.dist-info/entry_points.txt
ur_tunnel-0.0.13.dist-info/top_level.txt
ur_tunnel-0.0.13.dist-info/RECORD
