Metadata-Version: 2.1
Name: ur-tunnel
Version: 0.0.13
Requires-Dist: aiohttp
Requires-Dist: certifi
Requires-Dist: websockets
Requires-Dist: packaging
